iocingestor/__init__.py
iocingestor/artifacts/__init__.py
iocingestor/artifacts/artifact.py
iocingestor/artifacts/domain.py
iocingestor/artifacts/hash.py
iocingestor/artifacts/ip_address.py
iocingestor/artifacts/task.py
iocingestor/artifacts/url.py
iocingestor/config.py
iocingestor/exceptions.py
iocingestor/extras/__init__.py
iocingestor/extras/api.py
iocingestor/extras/public/index.html
iocingestor/extras/public/list.html
iocingestor/extras/webapp.py
iocingestor/ioc_fanger/__init__.py
iocingestor/ioc_fanger/fang.json
iocingestor/ioc_fanger/grammars.py
iocingestor/operators/__init__.py
iocingestor/operators/abstract_json.py
iocingestor/operators/csv.py
iocingestor/operators/misp.py
iocingestor/operators/sqlite.py
iocingestor/schemas.py
iocingestor/sources/__init__.py
iocingestor/sources/abstract_json.py
iocingestor/sources/github.py
iocingestor/sources/rss.py
iocingestor/sources/twitter.py
iocingestor/sources/web.py
iocingestor/state.py
iocingestor/whitelists/__init__.py
iocingestor-0.3.3.dist-info/entry_points.txt
iocingestor-0.3.3.dist-info/LICENSE
iocingestor-0.3.3.dist-info/WHEEL
iocingestor-0.3.3.dist-info/METADATA
iocingestor-0.3.3.dist-info/RECORD
