Metadata-Version: 2.1
Name: iocingestor
Version: 0.3.3
Summary: Extract and aggregate IOCs from threat feeds.
Home-page: https://github.com/ninoseki/iocingestor
License: GPL-2.0-or-later
Author: Manabu Niseki
Author-email: manabu.niseki@gmail.com
Requires-Python: >=3.6.2,<4.0.0
Classifier: License :: OSI Approved :: GNU General Public License v2 or later (GPLv2+)
Classifier: Programming Language :: Python :: 3
Classifier: Programming Language :: Python :: 3.7
Classifier: Programming Language :: Python :: 3.8
Classifier: Programming Language :: Python :: 3.9
Requires-Dist: PyYAML (>=5.4.1,<6.0.0)
Requires-Dist: aiocontextvars (>=0.2.2,<0.3.0)
Requires-Dist: async-exit-stack (>=1.0.1,<2.0.0)
Requires-Dist: async-generator (>=1.10,<2.0)
Requires-Dist: beautifulsoup4 (>=4.10.0,<5.0.0)
Requires-Dist: contextvars (>=2.4,<3.0)
Requires-Dist: environs (>=9.3.4,<10.0.0)
Requires-Dist: fastapi (>=0.70.0,<0.71.0)
Requires-Dist: fastapi-utils (>=0.2.1,<0.3.0)
Requires-Dist: feedparser (>=6.0.8,<7.0.0)
Requires-Dist: importlib-metadata (>=4.8.1,<5.0.0)
Requires-Dist: ioc-finder (>=6.0.1,<7.0.0)
Requires-Dist: iocextract (>=1.13.1,<2.0.0)
Requires-Dist: ipaddress (>=1.0.23,<2.0.0)
Requires-Dist: jsonpath-rw (>=1.4.0,<2.0.0)
Requires-Dist: loguru (>=0.5.3,<0.6.0)
Requires-Dist: pydantic (>=1.8,<2.0)
Requires-Dist: pymisp (>=2.4.131,<3.0.0)
Requires-Dist: pyparsing (>=2.4.7,<3.0.0)
Requires-Dist: requests (>=2.26.0,<3.0.0)
Requires-Dist: sgmllib3k (>=1.0.0,<2.0.0)
Requires-Dist: statsd (>=3.3.0,<4.0.0)
Requires-Dist: twitter (>=1.19.3,<2.0.0)
Requires-Dist: uvicorn[standard] (>=0.15.0,<0.16.0)
Project-URL: Repository, https://github.com/ninoseki/iocingestor
